discord/__init__.py
py_discord-0.0.1.dist-info/LICENSE
py_discord-0.0.1.dist-info/METADATA
py_discord-0.0.1.dist-info/WHEEL
py_discord-0.0.1.dist-info/top_level.txt
py_discord-0.0.1.dist-info/RECORD
