Metadata-Version: 2.1
Name: py-discord
Version: 0.0.1
Summary: A Discord API wrapper.
Home-page: https://github.com/MasterSteelblade/PyDiscord
License: UNKNOWN
Platform: UNKNOWN
Requires-Python: >=3.9.0
License-File: LICENSE
